README.md
setup.cfg
setup.py
fix2dict/__init__.py
fix2dict/__version__.py
fix2dict/basic_repository_v1.py
fix2dict/description.py
fix2dict/extension_pack.py
fix2dict/fix_version.py
fix2dict/patch.py
fix2dict/repository.py
fix2dict/resources.py
fix2dict/review.py
fix2dict/schema.py
fix2dict/sqlite.py
fix2dict/unified_repository_v1.py
fix2dict/utils.py
fix2dict.egg-info/PKG-INFO
fix2dict.egg-info/SOURCES.txt
fix2dict.egg-info/dependency_links.txt
fix2dict.egg-info/entry_points.txt
fix2dict.egg-info/requires.txt
fix2dict.egg-info/top_level.txt
fix2dict/cli/__init__.py
fix2dict/cli/deflate.py
fix2dict/cli/ep.py
fix2dict/cli/filter_patch.py
fix2dict/cli/fix_typos.py
fix2dict/cli/inflate.py
fix2dict/cli/main.py
fix2dict/cli/patch.py
fix2dict/cli/repo_b.py
fix2dict/cli/repo_o.py
fix2dict/cli/repo_u.py
fix2dict/cli/review.py
fix2dict/cli/schema.py
fix2dict/cli/sqlite.py
fix2dict/cli/validate.py
fix2dict/cli/xref.py
fix2dict/cli/utils/__init__.py
fix2dict/cli/utils/json.py
fix2dict/cli/utils/options.py
fix2dict/cli/utils/xml.py
fix2dict/resources/errata/fix-4-0.json
fix2dict/resources/errata/fix-4-1.json
fix2dict/resources/errata/fix-4-3.json
fix2dict/resources/errata/fix-4-4.json
fix2dict/resources/errata/improve-descriptions.json
fix2dict/resources/errata/ref-msg-type.json
fix2dict/resources/errata/typos.json
fix2dict/resources/schema/v1.json
fix2dict/resources/sql/setup.sql
fix2dict/resources/tests/abbreviations/1-detl.json
fix2dict/resources/tests/abbreviations/1-detl.xml
fix2dict/resources/tests/abbreviations/2-efp.json
fix2dict/resources/tests/abbreviations/2-efp.xml
fix2dict/resources/tests/abbreviations/3-with-usage.json
fix2dict/resources/tests/abbreviations/3-with-usage.xml
fix2dict/resources/tests/datatypes/1-length.json
fix2dict/resources/tests/datatypes/1-length.xml
fix2dict/resources/tests/datatypes/2-mkt-date.json
fix2dict/resources/tests/datatypes/2-mkt-date.xml
fix2dict/resources/tests/fields/1-ref-id.json
fix2dict/resources/tests/fields/1-ref-id.xml
fix2dict/xml_logic/__init__.py
fix2dict/xml_logic/elem_abbreviation.py
fix2dict/xml_logic/elem_category.py
fix2dict/xml_logic/elem_component.py
fix2dict/xml_logic/elem_datatype.py
