Metadata-Version: 2.1
Name: fix2dict
Version: 0.7.0
Summary: FIX Dictionary generator tool
Home-page: https://github.com/fixipe/fix2dict
Author: Filippo Costa @neysofu
Author-email: filippocosta.italy@gmail.com
License: Apache Software License
Keywords: FIX protocol XML fintech finance trading
Platform: UNKNOWN
Classifier: Development Status :: 5 - Production/Stable
Classifier: Intended Audience :: Developers
Classifier: License :: OSI Approved :: Apache Software License
Classifier: Programming Language :: Python :: 3.5
Classifier: Programming Language :: Python :: 3.6
Classifier: Programming Language :: Python :: 3.7
Classifier: Programming Language :: Python :: 3.8
Requires-Python: >=3.5
